[
    1,
    [
        "74rhwlJv9MLLukRD6j/o6f@6c48a"
    ],
    [
        "_textureSource"
    ],
    [
        "cc.SpriteFrame"
    ],
    0,
    [
        {
            "name": "beginGame",
            "rect": {
                "x": 14,
                "y": 16,
                "width": 276,
                "height": 120
            },
            "offset": {
                "x": 2,
                "y": -1
            },
            "originalSize": {
                "width": 300,
                "height": 150
            },
            "rotated": false,
            "capInsets": [
                0,
                0,
                0,
                0
            ],
            "vertices": {
                "rawPosition": [
                    -138,
                    -60,
                    0,
                    138,
                    -60,
                    0,
                    -138,
                    60,
                    0,
                    138,
                    60,
                    0
                ],
                "indexes": [
                    0,
                    1,
                    2,
                    2,
                    1,
                    3
                ],
                "uv": [
                    14,
                    134,
                    290,
                    134,
                    14,
                    14,
                    290,
                    14
                ],
                "nuv": [
                    0.04666666666666667,
                    0.09333333333333334,
                    0.9666666666666667,
                    0.09333333333333334,
                    0.04666666666666667,
                    0.8933333333333333,
                    0.9666666666666667,
                    0.8933333333333333
                ],
                "minPos": {
                    "x": -138,
                    "y": -60,
                    "z": 0
                },
                "maxPos": {
                    "x": 138,
                    "y": 60,
                    "z": 0
                }
            },
            "packable": true,
            "pixelsToUnit": 100,
            "pivot": {
                "x": 0.5,
                "y": 0.5
            },
            "meshType": 0
        }
    ],
    [
        0
    ],
    0,
    [
        0
    ],
    [
        0
    ],
    [
        0
    ]
]
